bloodhound_cli/__init__.py
bloodhound_cli/__main__.py
bloodhound_cli/main.py
bloodhound_cli/old_main.py
bloodhound_cli/core/__init__.py
bloodhound_cli/core/base.py
bloodhound_cli/core/ce.py
bloodhound_cli/core/factory.py
bloodhound_cli/core/legacy.py
bloodhound_cli/core/logging_utils.py
bloodhound_cli/core/settings.py
bloodhound_cli-1.2.6.dist-info/licenses/LICENSE
bloodhound_cli-1.2.6.dist-info/METADATA
bloodhound_cli-1.2.6.dist-info/WHEEL
bloodhound_cli-1.2.6.dist-info/entry_points.txt
bloodhound_cli-1.2.6.dist-info/top_level.txt
bloodhound_cli-1.2.6.dist-info/RECORD
