Metadata-Version: 2.4
Name: bloodhound-cli
Version: 1.2.6
Summary: CLI for querying BloodHound data (Legacy Neo4j + CE skeleton).
Author-email: ADScan <github@adscanpro.com>
License: MIT
Keywords: bloodhound,neo4j,ad,active directory,pentesting
Classifier: Programming Language :: Python :: 3
Classifier: License :: OSI Approved :: MIT License
Classifier: Operating System :: OS Independent
Requires-Python: >=3.9
License-File: LICENSE
Requires-Dist: neo4j>=5.0.0
Requires-Dist: requests>=2.31.0
Requires-Dist: rich>=13.7.0
Requires-Dist: structlog>=24.1.0
Requires-Dist: pydantic-settings>=2.4.0
Provides-Extra: dev
Requires-Dist: pytest<9.0,>=8.3; extra == "dev"
Requires-Dist: pylint<3.4,>=3.3; extra == "dev"
Requires-Dist: ruff>=0.5.0; extra == "dev"
Requires-Dist: build>=1.2.2; extra == "dev"
Dynamic: license-file
